coopstructs/__init__.py
coopstructs/sectorTree.py
coopstructs/geometry/__init__.py
coopstructs/geometry/exceptions.py
coopstructs/geometry/logger.py
coopstructs/geometry/polygonRegion.py
coopstructs/geometry/circles/__init__.py
coopstructs/geometry/circles/circle.py
coopstructs/geometry/curves/__init__.py
coopstructs/geometry/curves/curveBoundaryFactory.py
coopstructs/geometry/curves/curveBuilder.py
coopstructs/geometry/curves/curveTrace.py
coopstructs/geometry/curves/curve_factory.py
coopstructs/geometry/curves/curves.py
coopstructs/geometry/curves/enums.py
coopstructs/geometry/lines/__init__.py
coopstructs/geometry/lines/line.py
coopstructs/geometry/rectangles/__init__.py
coopstructs/geometry/rectangles/rectangle.py
coopstructs/geometry/triangles/__init__.py
coopstructs/geometry/triangles/triangle.py
coopstructs/geometry/vectors/__init__.py
coopstructs/geometry/vectors/vectorN.py
coopstructs/geometry/vectors/vector_utils.py
coopstructs/zones/__init__.py
coopstructs/zones/exceptions.py
coopstructs/zones/logger.py
coopstructs/zones/zoneManager.py
coopstructs-2.2.dist-info/LICENSE
coopstructs-2.2.dist-info/METADATA
coopstructs-2.2.dist-info/WHEEL
coopstructs-2.2.dist-info/top_level.txt
coopstructs-2.2.dist-info/RECORD
