Metadata-Version: 2.1
Name: coopstructs
Version: 2.2
Summary: Basic data structs commonly used by various applications
Home-page: https://github.com/tylertjburns/coopstructs
Author: tburns
Author-email: tyler.tj.burns@gmail.com
License: MIT
Classifier: Development Status :: 3 - Alpha
Classifier: License :: OSI Approved :: MIT License
Classifier: Programming Language :: Python
Classifier: Programming Language :: Python :: 3.5
Classifier: Programming Language :: Python :: 3.6
Classifier: Topic :: Software Development :: Libraries
Classifier: Topic :: Software Development :: Libraries :: Python Modules
Classifier: Intended Audience :: Developers
Requires-Python: >3.5
License-File: LICENSE
Requires-Dist: certifi ==2024.7.4
Requires-Dist: charset-normalizer ==3.3.2
Requires-Dist: contourpy ==1.3.2
Requires-Dist: cooptools ==1.45
Requires-Dist: cycler ==0.12.1
Requires-Dist: docutils ==0.21.2
Requires-Dist: fonttools ==4.58.4
Requires-Dist: idna ==3.7
Requires-Dist: importlib-metadata ==8.0.0
Requires-Dist: jaraco.classes ==3.4.0
Requires-Dist: jaraco.context ==5.3.0
Requires-Dist: jaraco.functools ==4.0.1
Requires-Dist: keyring ==25.2.1
Requires-Dist: kiwisolver ==1.4.8
Requires-Dist: markdown-it-py ==3.0.0
Requires-Dist: matplotlib ==3.10.3
Requires-Dist: mdurl ==0.1.2
Requires-Dist: more-itertools ==10.3.0
Requires-Dist: nh3 ==0.2.18
Requires-Dist: numpy ==2.3.0
Requires-Dist: packaging ==25.0
Requires-Dist: pandas ==2.3.0
Requires-Dist: pillow ==11.2.1
Requires-Dist: pkginfo ==1.10.0
Requires-Dist: Pygments ==2.18.0
Requires-Dist: pyparsing ==3.2.3
Requires-Dist: python-dateutil ==2.9.0.post0
Requires-Dist: pytz ==2025.2
Requires-Dist: pywin32-ctypes ==0.2.2
Requires-Dist: readme-renderer ==44.0
Requires-Dist: requests ==2.32.3
Requires-Dist: requests-toolbelt ==1.0.0
Requires-Dist: rfc3986 ==2.0.0
Requires-Dist: rich ==13.7.1
Requires-Dist: scipy ==1.15.3
Requires-Dist: setuptools ==70.3.0
Requires-Dist: shapely ==2.1.1
Requires-Dist: six ==1.17.0
Requires-Dist: twine ==5.1.1
Requires-Dist: tzdata ==2025.2
Requires-Dist: urllib3 ==2.2.2
Requires-Dist: zipp ==3.19.2
